<?xml version = '1.0' encoding = 'UTF-8'?>
<FKIndexAssociation class="oracle.dbtools.crest.model.design.relational.FKIndexAssociation" directorySegmentName="seg_0" id="C1A6520E-8991-5C30-C8B1-6E3731E78DBD" containerWithKeyObject="465ACF5F-71D9-ADB6-33FE-3DB608FDF2CD" localFKIndex="644EF593-7BFE-B6B2-2396-CC621ED6AB68" name="SYS_C007401">
<sourceConnName>BI</sourceConnName>
<sourceObjSchema>BI</sourceObjSchema>
<sourceObjName>SYS_C007401</sourceObjName>
<createdBy>torkun</createdBy>
<createdTime>2019-05-14 00:24:11 UTC</createdTime>
<ownerDesignName>des</ownerDesignName>
<referredTableLongName>BI.SATIS</referredTableLongName>
<deleteRule>NO ACTION</deleteRule>
<referredTableID>BB013396-43C7-71A3-48BD-CEA60F31629C</referredTableID>
<keyObject>F421A08D-8A8E-8D75-DAAD-BD4EE937B3C0</keyObject>
<referredKeyID>F421A08D-8A8E-8D75-DAAD-BD4EE937B3C0</referredKeyID>
<mandatory>false</mandatory>
<refColNames>FISNO</refColNames>
<transferable>true</transferable>
<rely>false</rely>
<columnDependencyConstraintGenerateInDDL>true</columnDependencyConstraintGenerateInDDL>
</FKIndexAssociation>